masonite/dot/__init__.py
masonite/dot/dot.py
masonite_dot-0.0.5.dist-info/METADATA
masonite_dot-0.0.5.dist-info/WHEEL
masonite_dot-0.0.5.dist-info/top_level.txt
masonite_dot-0.0.5.dist-info/RECORD
